hackathon_sakhi/__init__.py
hackathon_sakhi/location.py
hackathon_sakhi/location_v2.py
hackathon_sakhi/telegram.py
hackathon_sakhi/weather.py
hackathon_sakhi/news/__init__.py
hackathon_sakhi/news/clustering.py
hackathon_sakhi/news/fetcher.py
hackathon_sakhi/news/models.py
hackathon_sakhi/news/processor.py
hackathon_sakhi/news/server.py
hackathon_sakhi/news/sources.py
hackathon_sakhi-0.2.2.dist-info/METADATA
hackathon_sakhi-0.2.2.dist-info/WHEEL
hackathon_sakhi-0.2.2.dist-info/entry_points.txt
hackathon_sakhi-0.2.2.dist-info/licenses/LICENSE
hackathon_sakhi-0.2.2.dist-info/RECORD
