Metadata-Version: 2.4
Name: hackathon-sakhi
Version: 0.2.2
Summary: Women Safety MCP Servers - Hackathon Project (Weather, News Dashboard, Telegram Alerts, Location Monitor)
Project-URL: Homepage, https://github.com/yourusername/hackathon-sakhi
Project-URL: Repository, https://github.com/yourusername/hackathon-sakhi
Author: Hackathon Team
License-Expression: MIT
License-File: LICENSE
Keywords: hackathon,mcp,news,telegram,weather,women-safety
Classifier: Development Status :: 3 - Alpha
Classifier: Intended Audience :: Developers
Classifier: License :: OSI Approved :: MIT License
Classifier: Programming Language :: Python :: 3
Classifier: Programming Language :: Python :: 3.10
Classifier: Programming Language :: Python :: 3.11
Classifier: Programming Language :: Python :: 3.12
Requires-Python: >=3.10
Requires-Dist: feedparser>=6.0.0
Requires-Dist: mcp>=1.0.0
Requires-Dist: python-dotenv>=1.0.0
Requires-Dist: requests>=2.31.0
Provides-Extra: dev
Requires-Dist: pytest-asyncio>=0.21.0; extra == 'dev'
Requires-Dist: pytest>=7.0.0; extra == 'dev'
